cms_saq
