Metadata-Version: 1.0
Name: django-cms-saq
Version: 0.2.3
Summary: Self-assessment questionnaires with Django CMS.
Home-page: https://github.com/Maplecroft/django-cms-saq
Author: Maplecroft
Author-email: james.rutherford@maplecroft.com
License: LICENSE.txt
Platform: UNKNOWN
